UltrasonicUSBDemo/__init__.py
UltrasonicUSBDemo/__main__.py
UltrasonicUSBDemo/fs0002.xml
UltrasonicUSBDemo/fs000x.xml
UltrasonicUSBDemo/image/UM0034_banner.png
UltrasonicUSBDemo/image/UM0090_banner.png
UltrasonicUSBDemo/image/fs000x_banner.png
UltrasonicUSBDemo/image/um0017_banner.png
UltrasonicUSBDemo-1.6.9.dist-info/METADATA
UltrasonicUSBDemo-1.6.9.dist-info/WHEEL
UltrasonicUSBDemo-1.6.9.dist-info/top_level.txt
UltrasonicUSBDemo-1.6.9.dist-info/RECORD
