Metadata-Version: 2.1
Name: UltrasonicUSBDemo
Version: 1.6.9
Summary: Demonstrates communication with different USB ultrasonic devices
Home-page: https://github.com/RoanokeControls/PkgUltrasonicUSBDemo
Author: Roanoke Electronic Controls, Inc.
Author-email: info@roanokecontrols.com
License: UNKNOWN
Platform: UNKNOWN
Classifier: Programming Language :: Python :: 3
Classifier: License :: OSI Approved :: GNU General Public License v3 (GPLv3)
Classifier: Operating System :: OS Independent
Requires-Python: >=3.6
Requires-Dist: PyQt5
Requires-Dist: pyserial
